{
    "between": -1668752059,
    "mean": {
      "consist": "birds",
      "cowboy": {
        "uncle": -56090026.02982664,
        "function": "ordinary",
        "tall": "throat",
        "suddenly": {
          "special": "yes",
          "bar": 1096181403.977048,
          "cry": -10095015.754611492,
          "chamber": 2001213613.818328
        }
      },
      "ordinary": "coal",
      "safety": {
        "nodded": -1554277510,
        "slept": 18454097.06285572,
        "fight": {
          "straw": "pictured",
          "tree": 1467516144.3692708,
          "older": -1113715352,
          "hard": {
            "dark": 684406472,
            "combine": 1884992709.8610115,
            "spell": -316689508,
            "suddenly": -1110807307.92133
          }
        },
        "heart": "animal"
      }
    },
    "mathematics": 1655885123,
    "pass": "there"
  }